cafe/__init__.py
cafe/abc/__init__.py
cafe/abc/compat.py
cafe/compat.py
cafe/datastructs/__init__.py
cafe/datastructs/dict.py
cafe/datastructs/memory.py
cafe/datastructs/units/__init__.py
cafe/datastructs/units/data.py
cafe/decorators/__init__.py
cafe/logging/__init__.py
cafe/logging/trace.py
cafe/patterns/__init__.py
cafe/patterns/borg.py
cafe/patterns/context/__init__.py
cafe/patterns/mixins.py
cafe/twisted/__init__.py
cafe/utilities.py
python_cafe-0.17.0.dist-info/LICENSE
python_cafe-0.17.0.dist-info/WHEEL
python_cafe-0.17.0.dist-info/METADATA
python_cafe-0.17.0.dist-info/RECORD
