Metadata-Version: 2.1
Name: python-cafe
Version: 0.17.0
Summary: Python Cafe: A convenience package providing various building blocks enabling pythonic patterns.
Home-page: https://github.com/abn/python-cafe
License: UNKNOWN
Author: Arun Babu Neelicattu
Author-email: arun.neelicattu@gmail.com
Requires-Python: >=2.7, !=3.0.*, !=3.1.*, !=3.2.*, !=3.3.*
Classifier: Intended Audience :: Developers
Classifier: License :: OSI Approved :: Apache Software License
Classifier: Operating System :: OS Independent
Classifier: Programming Language :: Python
Classifier: Programming Language :: Python :: 2
Classifier: Programming Language :: Python :: 2.7
Classifier: Programming Language :: Python :: 3
Classifier: Programming Language :: Python :: 3.4
Classifier: Programming Language :: Python :: 3.5
Classifier: Programming Language :: Python :: 3.6
Classifier: Programming Language :: Python :: 3.7
Classifier: Topic :: Software Development :: Libraries :: Python Modules
Requires-Dist: PyYAML (>=3.13,<4.0)
Requires-Dist: enum34 (>=1.1,<2.0); python_version >= "2.7" and python_version < "2.8"
Requires-Dist: six (>=1.12,<2.0)
Project-URL: Repository, https://github.com/abn/python-cafe
